setup.py
brynq_sdk_profit/__init__.py
brynq_sdk_profit/address.py
brynq_sdk_profit/afas.py
brynq_sdk_profit/bankaccount.py
brynq_sdk_profit/contract.py
brynq_sdk_profit/costcarrier.py
brynq_sdk_profit/costcenter.py
brynq_sdk_profit/custom_connector.py
brynq_sdk_profit/debtor_creditor.py
brynq_sdk_profit/employees.py
brynq_sdk_profit/family.py
brynq_sdk_profit/functions.py
brynq_sdk_profit/journalentry.py
brynq_sdk_profit/leaves.py
brynq_sdk_profit/organisation.py
brynq_sdk_profit/organisational_unit.py
brynq_sdk_profit/payslips.py
brynq_sdk_profit/person.py
brynq_sdk_profit/postcalculation.py
brynq_sdk_profit/salaries.py
brynq_sdk_profit/sick_leaves.py
brynq_sdk_profit/wage_components.py
brynq_sdk_profit/wage_mutations.py
brynq_sdk_profit.egg-info/PKG-INFO
brynq_sdk_profit.egg-info/SOURCES.txt
brynq_sdk_profit.egg-info/dependency_links.txt
brynq_sdk_profit.egg-info/not-zip-safe
brynq_sdk_profit.egg-info/requires.txt
brynq_sdk_profit.egg-info/top_level.txt
brynq_sdk_profit/legacy/profit_data_cleaner.py
brynq_sdk_profit/legacy/profit_get.py
brynq_sdk_profit/legacy/profit_get_async.py
brynq_sdk_profit/legacy/profit_update.py
brynq_sdk_profit/schemas/__init__.py
brynq_sdk_profit/schemas/address.py
brynq_sdk_profit/schemas/applicant.py
brynq_sdk_profit/schemas/bank_account.py
brynq_sdk_profit/schemas/calculations.py
brynq_sdk_profit/schemas/contact.py
brynq_sdk_profit/schemas/contract.py
brynq_sdk_profit/schemas/cost.py
brynq_sdk_profit/schemas/creditor.py
brynq_sdk_profit/schemas/date.py
brynq_sdk_profit/schemas/debit_credit.py
brynq_sdk_profit/schemas/debtor.py
brynq_sdk_profit/schemas/document.py
brynq_sdk_profit/schemas/dosseritem.py
brynq_sdk_profit/schemas/employee.py
brynq_sdk_profit/schemas/family.py
brynq_sdk_profit/schemas/formation_distribution.py
brynq_sdk_profit/schemas/function.py
brynq_sdk_profit/schemas/leaves.py
brynq_sdk_profit/schemas/organisation.py
brynq_sdk_profit/schemas/payslip.py
brynq_sdk_profit/schemas/person.py
brynq_sdk_profit/schemas/salary.py
brynq_sdk_profit/schemas/subscription.py
brynq_sdk_profit/schemas/timetable.py
brynq_sdk_profit/schemas/user.py
brynq_sdk_profit/schemas/wage.py
brynq_sdk_profit/schemas/workschedule.py