Metadata-Version: 1.0
Name: brynq-sdk-profit
Version: 4.1.4
Summary: Profit wrapper from BrynQ
Home-page: UNKNOWN
Author: BrynQ
Author-email: support@brynq.com
License: BrynQ License
Platform: UNKNOWN
